tersel/Option.py
tersel/OptionList.py
tersel/__init__.py
tersel-0.0.3.dist-info/LICENSE
tersel-0.0.3.dist-info/METADATA
tersel-0.0.3.dist-info/WHEEL
tersel-0.0.3.dist-info/top_level.txt
tersel-0.0.3.dist-info/RECORD
